houdini_package_manager/__init__.py
houdini_package_manager/main.py
houdini_package_manager/meta/meta_tools.py
houdini_package_manager/meta/user_data_manager.py
houdini_package_manager/resources/fonts/Lato-Black.ttf
houdini_package_manager/resources/fonts/Lato-BlackItalic.ttf
houdini_package_manager/resources/fonts/Lato-Bold.ttf
houdini_package_manager/resources/fonts/Lato-BoldItalic.ttf
houdini_package_manager/resources/fonts/Lato-Italic.ttf
houdini_package_manager/resources/fonts/Lato-Light.ttf
houdini_package_manager/resources/fonts/Lato-LightItalic.ttf
houdini_package_manager/resources/fonts/Lato-Medium.ttf
houdini_package_manager/resources/fonts/Lato-MediumItalic.ttf
houdini_package_manager/resources/fonts/Lato-Regular.ttf
houdini_package_manager/resources/icons/add.svg
houdini_package_manager/resources/icons/add_hover.svg
houdini_package_manager/resources/icons/add_packages.svg
houdini_package_manager/resources/icons/add_packages_confirm.svg
houdini_package_manager/resources/icons/add_packages_confirm_hover.svg
houdini_package_manager/resources/icons/add_packages_hover.svg
houdini_package_manager/resources/icons/bug.svg
houdini_package_manager/resources/icons/bug_hover.svg
houdini_package_manager/resources/icons/clear_selection.svg
houdini_package_manager/resources/icons/clear_selection_hover.svg
houdini_package_manager/resources/icons/delete.svg
houdini_package_manager/resources/icons/delete_hover.svg
houdini_package_manager/resources/icons/docs.svg
houdini_package_manager/resources/icons/docs_hover.svg
houdini_package_manager/resources/icons/file.svg
houdini_package_manager/resources/icons/file_hover.svg
houdini_package_manager/resources/icons/folder.svg
houdini_package_manager/resources/icons/folder_hover.svg
houdini_package_manager/resources/icons/gear.svg
houdini_package_manager/resources/icons/gear_hover.svg
houdini_package_manager/resources/icons/gear_white.svg
houdini_package_manager/resources/icons/git_sync.svg
houdini_package_manager-2.2.13.dist-info/METADATA
houdini_package_manager-2.2.13.dist-info/WHEEL
houdini_package_manager-2.2.13.dist-info/licenses/LICENSE
houdini_package_manager-2.2.13.dist-info/RECORD
