Metadata-Version: 2.4
Name: houdini_package_manager
Version: 2.2.13
Summary: GUI package manager for Houdini
License-File: LICENSE
Author: Ariff Jeff
Author-email: ariffjeff@icloud.com
Requires-Python: >=3.11,<3.12
Classifier: Programming Language :: Python :: 3
Classifier: Programming Language :: Python :: 3.11
Requires-Dist: gitpython (>=3.1.43,<4.0.0)
Requires-Dist: packaging (>=24.2,<25.0)
Requires-Dist: pyside6 (>=6.4.2,<7.0.0)
Requires-Dist: requests (>=2.30.0,<3.0.0)
Project-URL: Documentation, https://ariffjeff.github.io/houdini-package-manager/
Project-URL: Repository, https://github.com/ariffjeff/houdini-package-manager
